captchafox/__init__.py
captchafox/browser/__init__.py
captchafox/browser/captchafox.py
captchafox/captcha/__init__.py
captchafox/fingerprints/__init__.py
captchafox/generatoroptions/__init__.py
captchafox/generatoroptions/config.py
captchafox/generatoroptions/generatoroptions.py
captchafox/generatoroptions/os.py
captchafox/generatoroptions/screen.py
captchafox/generatoroptions/webgl_config.py
captchafox/integration/__init__.py
captchafox/network/__init__.py
captchafox-0.10.0.dist-info/METADATA
captchafox-0.10.0.dist-info/WHEEL
captchafox-0.10.0.dist-info/top_level.txt
captchafox-0.10.0.dist-info/RECORD
