Metadata-Version: 2.4
Name: captchafox
Version: 0.10.0
Summary: PyPI package based on camoufox with native captcha passing functions and the ability to switch to selenium_driverless (for the browser GUI) for development
Project-URL: Homepage, https://github.com/Triram-2/captchafox
Requires-Python: >=3.12
Requires-Dist: uvloop
Requires-Dist: camoufox[geoip]
Requires-Dist: httpx
Provides-Extra: lint
Requires-Dist: ruff; extra == "lint"
Requires-Dist: pyright; extra == "lint"
Provides-Extra: test
Requires-Dist: captchafox; extra == "test"
Requires-Dist: pytest; extra == "test"
Requires-Dist: pytest-asyncio; extra == "test"
Requires-Dist: coverage[toml]; extra == "test"
Provides-Extra: profile
Requires-Dist: scalene; extra == "profile"
Provides-Extra: audit
Requires-Dist: pip-audit; extra == "audit"
Provides-Extra: docs
Requires-Dist: sphinx; extra == "docs"
Requires-Dist: sphinx-rtd-theme; extra == "docs"
Provides-Extra: dev
Requires-Dist: nox; extra == "dev"
Requires-Dist: commitizen; extra == "dev"
Requires-Dist: hatch; extra == "dev"
Provides-Extra: all
Requires-Dist: captchafox[lint]; extra == "all"
Requires-Dist: captchafox[test]; extra == "all"
Requires-Dist: captchafox[profile]; extra == "all"
Requires-Dist: captchafox[audit]; extra == "all"
Requires-Dist: captchafox[docs]; extra == "all"
Requires-Dist: captchafox[dev]; extra == "all"
